<?xml version="1.0" encoding="UTF-8"?>
<databaseChangeLog
  xmlns="http://www.liquibase.org/xml/ns/dbchangelog"
  xmlns:xsi="http://www.w3.org/2001/XMLSchema-instance"
  xsi:schemaLocation="http://www.liquibase.org/xml/ns/dbchangelog
                      http://www.liquibase.org/xml/ns/dbchangelog/dbchangelog-3.4.xsd"
  logicalFilePath="changelog-trips-type">

  <changeSet author="Marco Grams" id="changelog-trips-type">

    <preConditions onFail="MARK_RAN">
      <tableExists tableName="tc_trips" />
    </preConditions>

    <addColumn tableName="tc_trips">
      <column name="type" type="TINYINT" defaultValueNumeric="0">
        <constraints nullable="false" />
      </column>
    </addColumn>

  </changeSet>

</databaseChangeLog>
